LICENSE.txt
MANIFEST.in
README.rst
setup.py
pylr2/__init__.py
pylr2/regress2.py
pylr2.egg-info/PKG-INFO
pylr2.egg-info/SOURCES.txt
pylr2.egg-info/dependency_links.txt
pylr2.egg-info/requires.txt
pylr2.egg-info/top_level.txt
pylr2.egg-info/zip-safe