Metadata-Version: 1.1
Name: pylr2
Version: 0.1.0
Summary: Linear Regression Type II Models
Home-page: https://github.com/OceanOptics/pylr2.git
Author: Nils Haentjens
Author-email: nils.haentjens@maine.edu
License: MIT
Keywords: lr2 regress2 regression fit
Platform: UNKNOWN
Classifier: Development Status :: 3 - Alpha
Classifier: Intended Audience :: Education
Classifier: Intended Audience :: Science/Research
Classifier: License :: OSI Approved :: MIT License
Classifier: Programming Language :: Python :: 3
Classifier: Programming Language :: Python :: 3.6
